backtesting_pp2/__init__.py
backtesting_pp2/type2.py
backtesting_pp2-0.0.3.dist-info/METADATA
backtesting_pp2-0.0.3.dist-info/WHEEL
backtesting_pp2-0.0.3.dist-info/top_level.txt
backtesting_pp2-0.0.3.dist-info/RECORD
